deploy_django_nginx/__init__.py
deploy_django_nginx/build.py
deploy_django_nginx/config.py
deploy_django_nginx/main.py
deploy_django_nginx/setup_cython.py
deploy_django_nginx/util.py
deploy_django_nginx/version.json
deploy_django_nginx-1.0.2.dist-info/METADATA
deploy_django_nginx-1.0.2.dist-info/WHEEL
deploy_django_nginx-1.0.2.dist-info/entry_points.txt
deploy_django_nginx-1.0.2.dist-info/top_level.txt
deploy_django_nginx-1.0.2.dist-info/RECORD
