Metadata-Version: 2.1
Name: deploy-django-nginx
Version: 1.0.2
Summary: Deploy Django with uWSGI and Frontend with Nginx
Home-page: https://github.com/suqingdong/deploy_django_nginx
Author: suqingdong
Author-email: suqingdong1114@gmail.com
License: MIT License
Platform: UNKNOWN
Classifier: Development Status :: 5 - Production/Stable
Classifier: Operating System :: OS Independent
Classifier: Intended Audience :: Developers
Classifier: License :: OSI Approved :: MIT License
Classifier: Programming Language :: Python
Classifier: Programming Language :: Python :: 3
Classifier: Programming Language :: Python :: 3.8
Classifier: Programming Language :: Python :: 3.9
Classifier: Topic :: Software Development :: Libraries
Requires-Dist: click
Requires-Dist: Cython
Requires-Dist: webrequests
